<?xml version="1.0" encoding="UTF-8"?>
<?xml-model href="../../schema/identified-entities.rng" type="application/xml" schematypens="http://relaxng.org/ns/structure/1.0"?>
<person xmlns="http://www.tei-c.org/ns/1.0" xml:id="NA10029">
   <persName>
      <forename>James</forename>
      <surname>Wallace</surname>
   </persName>
   <note type="dates">
      <date>fl 1684 - 1724</date>
   </note>
   <sex value="M"/>
   <note type="biography">
      <p>Birth: Fl. 1684</p>
      <p>Death: 1724</p>
      
      <p>He was the eldest son of James Wallace, a minister in Orkney. He qualified M.D., and took part in the Darien scheme. He passed some plants from what is now Panama to James Petiver, and Hans Sloane. He became Fellow of the Royal Society, and had some employment with the East India Company. His later life is obscure.</p>
      
      <p>Membership</p>
      <p>Fellow</p>
      <p>Election Date:</p>
   </note>
   <note type="sources">
      <p>DNB</p>
   </note>
</person>