<?xml version="1.0" encoding="UTF-8"?>
<?xml-model href="../../schema/identified-entities.rng" type="application/xml" schematypens="http://relaxng.org/ns/structure/1.0"?>
<person xmlns="http://www.tei-c.org/ns/1.0" xml:id="NA1227">
   <persName>
      <forename>Ernest William</forename>
      <surname>Barnes</surname>
   </persName>
   <note type="dates">
      <date>1874 - 1953</date>
   </note>
   <sex value="M"/>
   <note type="biography">
      <p>Birth: 01 April 1874</p>
      <p>Death: 29 November 1953</p>
      
      <p>Education: King Edward VII School, Birmingham; ScD; MA</p>
      
      <p>Membership: Fellow</p>
      <p>Election Date: 6/05/1909</p>
   </note>
   <note type="sources">
      <p>Sources: Bulloch's Roll</p>
      <p>Obituaries: Obituary Notices of Fellows of the Royal Society 1954 vol 9 pp 15-25, plate, by Edmund T Whittaker</p>
   </note>
</person>