<?xml version="1.0" encoding="UTF-8"?>
<?xml-model href="../../schema/identified-entities.rng" type="application/xml" schematypens="http://relaxng.org/ns/structure/1.0"?>
<person xmlns="http://www.tei-c.org/ns/1.0" xml:id="NA1486">
   <persName>
      <forename>Archibald</forename>
      <surname>Smith</surname>
   </persName>
   <note type="dates">
      <date>1813 - 1872</date>
   </note>
   <sex value="M"/>
   <note type="biography">
      <p>Birth: 10 August 1813</p>
      <p>Death: 26 December 1872</p>
      
      <p>Profession: Barrister</p>
      <p>Education: MA</p>
      <p>Career: Fellow, Trinity College, Cambridge</p>
      
      <p>Membership: Fellow</p>
      <p>Election Date: 5/06/1856</p>
      <p>Medals/Prizes: Royal Medal 1865</p>
      <p>Council: VP 1869-1870</p>
   </note>
   <note type="sources">
      <p>Sources: Bulloch's Roll</p>
      <p>Obituaries: Proc Roy Soc 1873-1874 vol 22 pp i-xxiv signed by W T</p>
      <p>Notes: Charles Babbage's signature under From General Knowledge has been crossed out</p>
   </note>
</person>