<?xml version="1.0" encoding="UTF-8"?>
<?xml-model href="../../schema/identified-entities.rng" type="application/xml" schematypens="http://relaxng.org/ns/structure/1.0"?>
<person xmlns="http://www.tei-c.org/ns/1.0" xml:id="NA1575">
   <persName>
      <forename>Pierre</forename>
      <surname>Lyonet</surname>
   </persName>
   <note type="dates">
      <date>1706 - 1789</date>
   </note>
   <sex value="M"/>
   <note type="biography">
      <p>Birth: Maastricht, Netherlands (21 July 1706)</p>
      <p>Death: The Hague, Netherlands (10 January 1789)</p>
      
      <p>Research Field: Entomology</p>
      
      <p>Membership: Fellow</p>
      <p>Election Date: 14/01/1748</p>
   </note>
   <note type="sources">
      <p>Sources: Bulloch's Roll; DSB</p>
   </note>
</person>