<?xml version="1.0" encoding="UTF-8"?>
<?xml-model href="../../schema/identified-entities.rng" type="application/xml" schematypens="http://relaxng.org/ns/structure/1.0"?>
<person xmlns="http://www.tei-c.org/ns/1.0" xml:id="NA1686">
   <persName>
      <forename>John</forename>
      <surname>Evans</surname>
   </persName>
   <note type="dates">
      <date>1823 - 1908</date>
   </note>
   <sex value="M"/>
   <note type="biography">
      <p>Birth: Britwell Court, Burnham, Buckinghamshire, England (17 November 1823)</p>
      <p>Death: Britwell, Berkhamsted common, Hertfordshire (31 May 1908)</p>
      <p>Burial: Abbot's Langley parish church, Hertfordshire</p>
      
      <p>Profession: Paper manufacturer</p>
      <p>Research Field: Geology, archaeology, palaeontology, numismatics</p>
      <p>Career: Entered paper manufactory business of John Dickinson &amp; Co, of Nash Mills, Hemel Hempstead; partner (1850-1885); studied and made personal collections in geology, archaeology and paleaontology, his meticulous research particularly focused on prehistoric flint implements, but his initial training derived from the Iron Age and Roman coinage as well as geology ; placed the study of numismatics on a scientific basis; became famous for his synthesis of the Palaeolithic finds from France and England published in 1859-1860; one of the earliest men of commerce to become an appreciated member of several learned societies in London and elsewhere, and often also entrusted with high-ranking offices; deeply invovled in international work within learned societies, especially the international congresses of prehistoric archaeology; mastered French, German, and Nordic languages; an expert on water percolation through his business interests; trustee of the British Museum, with which he was heavily involved, as well as the Blackmore Nuseum and St Albans Museum; died after an operation</p>
      <p>Honours: KCB 1892</p>
      <p>Memberships: FGS; FSA; AICE; FNS; Corresponding Member, Society d'Emulation d'Abbeville; Archaeological Society, Luxembourg</p>
      
      <p>Membership: Fellow</p>
      <p>Election Date: 2/06/1864</p>
      <p>Council: Treas 1878-1898; VP 1874-1875, 1878-1898</p>
   </note>
   <note type="sources">
      <p>Sources: Bulloch's Roll; DNB</p>
      <p>Obituaries: Proc Roy Soc Series B 1908 vol 80 pp l-lvi signed by A G</p>
      <p>Web site; http://johnevans.ashmolean.org</p>
   </note>
</person>