<?xml version="1.0" encoding="UTF-8"?>
<?xml-model href="../../schema/identified-entities.rng" type="application/xml" schematypens="http://relaxng.org/ns/structure/1.0"?>
<person xmlns="http://www.tei-c.org/ns/1.0" xml:id="NA2175">
   <persName>
      <forename>Gilbert Thomas</forename>
      <surname>Morgan</surname>
   </persName>
   <note type="dates">
      <date>1870 - 1940</date>
   </note>
   <sex value="M"/>
   <note type="biography">
      <p>Birth: 22 September 1870</p>
      <p>Death: 01 February 1940</p>
      
      <p>Research Field: Chemistry</p>
      <p>Education: DSc;</p>
      <p>Honours: OBE ; Kt 1936</p>
      <p>Memberships: FIC; ARCS</p>
      
      <p>Membership: Fellow</p>
      <p>Election Date: 6/05/1915</p>
   </note>
   <note type="sources">
      <p>Sources: Bulloch's Roll</p>
      <p>Obituaries: Obituary Notices of Fellows of the Royal Society 1939-1941 vol 3 pp 355-362, plate, by J C Irvine</p>
   </note>
</person>