<?xml version="1.0" encoding="UTF-8"?>
<?xml-model href="../../schema/identified-entities.rng" type="application/xml" schematypens="http://relaxng.org/ns/structure/1.0"?>
<person xmlns="http://www.tei-c.org/ns/1.0" xml:id="NA2415">
   <persName>
      <forename>Charles</forename>
      <surname>Feake</surname>
   </persName>
   <note type="dates">
      <date>c 1716 - 1762</date>
   </note>
   <sex value="M"/>
   <note type="biography">
      <p>Birth: 'Cossimbazar' (?Cossipur), India (c 1716)</p>
      <p>Death: 02 August 1762</p>
      
      <p>Profession: Physician</p>
      <p>Education: Private schools at Stoke Newington and Hackney, London; Caius College, Cambridge; MB (1738), MD (1743)</p>
      <p>Career: Physician to Guy's Hospital, London</p>
      <p>Memberships: FRCP (1745)</p>
      
      <p>Membership: Fellow</p>
      <p>Election Date: 26/01/1749</p>
   </note>
   <note type="sources">
      <p>Sources: Bulloch's Roll; Venn</p>
   </note>
</person>