<?xml version="1.0" encoding="UTF-8"?>
<?xml-model href="../../schema/identified-entities.rng" type="application/xml" schematypens="http://relaxng.org/ns/structure/1.0"?>
<person xmlns="http://www.tei-c.org/ns/1.0" xml:id="NA2713">
   <persName>
      <forename>Jean Charles Gallissard de</forename>
      <surname>Marignac</surname>
   </persName>
   <note type="dates">
      <date>1817 - 1894</date>
   </note>
   <sex value="M"/>
   <note type="biography">
      <p>Birth: Geneva, Switzerland (24 April 1817)</p>
      <p>Death: Geneva, Switzerland (15 April 1894)</p>
      
      <p>Research Field: Inorganic chemistry, physical chemistry</p>
      <p>Education: Ecole Polytechnique, Paris; Ecole des Mines, Paris</p>
      <p>Career: Professor of Chemistry, Academy of Geneva (1841-1878); Professor of Mineralogy, Academy of Geneva (1845-1878); determined the atomic weight of 28 elements</p>
      
      <p>Membership: Foreign Member</p>
      <p>Election Date: 12/05/1881</p>
      <p>Medals/Prizes: Davy Medal 1886</p>
   </note>
   <note type="sources">
      <p>Sources: Bulloch's Roll; DSB</p>
      <p>References: W P Griffith and P J T Morris, 'Charles Hatchett FRS (1765 - 1847), chemist and discoverer of niobium' in NR 2003 vol 57 pp 299 - 316</p>
   </note>
</person>