<?xml version="1.0" encoding="UTF-8"?>
<?xml-model href="../../schema/identified-entities.rng" type="application/xml" schematypens="http://relaxng.org/ns/structure/1.0"?>
<person xmlns="http://www.tei-c.org/ns/1.0" xml:id="NA3018">
   <persName>
      <forename>Thomas</forename>
      <surname>Finch</surname>
   </persName>
   <note type="dates">
      <date>1756 - 1810</date>
   </note>
   <sex value="M"/>
   <note type="biography">
      <p>Birth: 01 July 1756</p>
      <p>Death: 23 March 1810</p>
      
      <p>Profession: Barrister</p>
      <p>Research Field: Classics</p>
      <p>Education: Merchant Taylor's School; St John's College, Oxford</p>
      <p>Career: Fellow, St John's College, Oxford</p>
      
      <p>Membership: Fellow</p>
      <p>Election Date: 13/12/1804</p>
   </note>
   <note type="sources">
      <p>Sources: Bulloch's Roll</p>
      <p>Authority: Birth date from V Sillery, St John's College, Oxford</p>
   </note>
</person>