<?xml version="1.0" encoding="UTF-8"?>
<?xml-model href="../../schema/identified-entities.rng" type="application/xml" schematypens="http://relaxng.org/ns/structure/1.0"?>
<person xmlns="http://www.tei-c.org/ns/1.0" xml:id="NA3290">
   <persName>
      <forename>James</forename>
      <surname>Burrow</surname>
   </persName>
   <note type="dates">
      <date>1701 - 1782</date>
   </note>
   <sex value="M"/>
   <note type="biography">
      <p>Birth: 28 November 1701</p>
      <p>Death: Starborough Castle, in the parish of Lingfield, Surrey (05 November 1782)</p>
      
      <p>Honours: Kt 1773</p>
      
      <p>Membership: Fellow</p>
      <p>Election Date: 7/04/1737</p>
      <p>Council: PRS 1768 (Oct-Nov), 1772 (Jul-Nov); VP 1752-?, 1758-?, 1760-1768, 1769-1782</p>
   </note>
   <note type="sources">
      <p>Sources: Bulloch's Roll; DNB</p>
   </note>
</person>