<?xml version="1.0" encoding="UTF-8"?>
<?xml-model href="../../schema/identified-entities.rng" type="application/xml" schematypens="http://relaxng.org/ns/structure/1.0"?>
<person xmlns="http://www.tei-c.org/ns/1.0" xml:id="NA3458">
   <persName>
      <forename>Charles</forename>
      <surname>Tweedie</surname>
   </persName>
   <note type="dates">
      <date>fl 1799 - 1821</date>
   </note>
   <sex value="M"/>
   <note type="biography">
      <p>Career: Wrote "The conduct of Great Britain vindicated" (1799), and "Reflections on the present crisis in public affairs" (1803)</p>
      <p>Memberships: FSA</p>
      
      <p>Membership: Fellow</p>
      <p>Election Date: 14/01/1819</p>
      <p>Defaulted 1821 (JB 22 November 1821).</p>
   </note>
   <note type="sources">
      <p>Sources: Bulloch's Roll</p>
   </note>
</person>