<?xml version="1.0" encoding="UTF-8"?>
<?xml-model href="../../schema/identified-entities.rng" type="application/xml" schematypens="http://relaxng.org/ns/structure/1.0"?>
<person xmlns="http://www.tei-c.org/ns/1.0" xml:id="NA359">
   <persName>
      <forename>John</forename>
      <surname>Wilson</surname>
   </persName>
   <note type="dates">
      <date>c 1788 - 1870</date>
   </note>
   <sex value="M"/>
   <note type="biography">
      <p>Birth: 28 March 1788</p>
      <p>Death: 10 August 1870</p>
      <p>Buried in Brompton Cemetery</p>
      
      <p>Profession: Physician</p>
      <p>Education: MD</p>
      <p>Career: Inspector of Naval Hospitals and Fleets (by 1845)</p>
      
      <p>Membership: Fellow</p>
      <p>Election Date: 19/02/1846</p>
   </note>
   <note type="sources">
      <p>Sources: Bulloch's Roll</p>
   </note>
   <note type="keywords">
      <term>Physician</term>
   </note>
</person>