<?xml version="1.0" encoding="UTF-8"?>
<?xml-model href="../../schema/identified-entities.rng" type="application/xml" schematypens="http://relaxng.org/ns/structure/1.0"?>
<person xmlns="http://www.tei-c.org/ns/1.0" xml:id="NA480">
   <persName>
      <forename>William</forename>
      <surname>Oliver</surname>
   </persName>
   <note type="dates">
      <date>1695 - 1764</date>
   </note>
   <sex value="M"/>
   <note type="biography">
      <p>Birth: Ludgvan, Cornwall, England (04 August 1695)</p>
      <p>Death: Bath, Somerset (17 March 1764)</p>
      <p>Burial: Church of Weston, near Bath, Somerset; monumental inscription in Bath Abbey</p>
      
      <p>Profession: Physician; Author, medical</p>
      <p>Education: Pembroke College, Cambridge (admitted 1714); MB (1720), MD (1725); Leyden (admitted 1720)</p>
      <p>Career: Practised in Plymouth; moved to Bath (1725); Physician to the Bath Mineral Water Hospital (1741-1760); inventor of the Bath Oliver biscuit; shortly before his death he gave the recipe, along with ten sacks of the finest wheat flour and £100, to his coachman, who set up shop and made a fortune</p>
      
      <p>Membership: Fellow</p>
      <p>Election Date: 22/01/1730</p>
      <p>Proposers: William Derham, William Rutty, Cromwell Mortimer</p>
   </note>
   <note type="sources">
      <p>Sources: Bulloch's Roll; DNB; Innes Smith; Venn</p>
      <p>References: Gentleman's Magazine 1764, p147 (obituary)</p>
      <p>London Magazine 1764, p163 (obituary)</p>
   </note>
</person>