<?xml version="1.0" encoding="UTF-8"?>
<?xml-model href="../../schema/identified-entities.rng" type="application/xml" schematypens="http://relaxng.org/ns/structure/1.0"?>
<person xmlns="http://www.tei-c.org/ns/1.0" xml:id="NA543">
   <persName>
      <forename>Robert</forename>
      <surname>Marsham</surname>
   </persName>
   <persName type="additional" subtype="title">
      <roleName>2nd Baron Romney</roleName>
   </persName>
   <note type="dates">
      <date>1717 - 1793</date>
   </note>
   <sex value="M"/>
   <note type="biography">
      <p>Birth: 22 August 1717</p>
      <p>Death: 16 November 1793</p>
      
      <p>Membership: Fellow</p>
      <p>Election Date: 19/05/1757</p>
   </note>
   <note type="sources">
      <p>Sources: Bulloch's Roll (from GEC)</p>
   </note>
</person>