<?xml version="1.0" encoding="UTF-8"?>
<?xml-model href="../../schema/identified-entities.rng" type="application/xml" schematypens="http://relaxng.org/ns/structure/1.0"?>
<person xmlns="http://www.tei-c.org/ns/1.0" xml:id="NA5564">
   <persName>
      <forename>Frederick William</forename>
      <surname>Beechey</surname>
   </persName>
   <note type="dates">
      <date>1796 - 1856</date>
   </note>
   <sex value="M"/>
   <note type="biography">
      <p>Birth: 17 February 1796</p>
      <p>Death: 29 November 1856</p>
      
      <p>Career: Entered Royal Navy</p>
      
      <p>Membership: Fellow</p>
      <p>Election Date: 23/12/1824</p>
      <p>Council: VP 1855-1856</p>
   </note>
   <note type="sources">
      <p>Sources: Bulloch's Roll; DNB</p>
      <p>Obituaries: Proc Roy Soc 1856-1857 vol 8 pp 283-287</p>
      <p>References: D Carr Agnew, 'Robert Fitzroy and the myth of 'Marsden Square': Transatlantic rivalries in early marine meteorology' in NR 2004 vol 58 pp 21-46</p>
      <p>Sonia Bershad 'The Drawings and watercolours by F W Beechey 1796-1856 in the collection of the Arctic Institute of North America, university of Calgary' in Arctic, vol 33, no 2, June 1980 [X430/12]</p>
   </note>
   <note type="keywords">
      <term>Rear Admiral Geographer</term>
   </note>
</person>