<?xml version="1.0" encoding="UTF-8"?>
<?xml-model href="../../schema/identified-entities.rng" type="application/xml" schematypens="http://relaxng.org/ns/structure/1.0"?>
<person xmlns="http://www.tei-c.org/ns/1.0" xml:id="NA5741">
   <persName>
      <forename>Philip</forename>
      <surname>Ryley</surname>
   </persName>
   <note type="dates">
      <date> - 1733</date>
   </note>
   <sex value="M"/>
   <note type="biography">
      <p>Death: Norwich, Norfolk (25 January 1733)</p>
      
      <p>Career: Sergeant-at-Arms to the Lord Teasurer of England (to 1702, 1706); Agent of the Exchequer; Commissioner of Excise (1698); Commissioner for collecting the duties on hides (1711); Surveyor of the Royal Woods and Forests</p>
      <p>Honours: Kt 1728</p>
      
      <p>Membership: Fellow</p>
      <p>Election Date: 15/07/1696</p>
   </note>
   <note type="sources">
      <p>Sources: Bulloch's Roll; DNB (William Ryley d 1667)</p>
   </note>
</person>