<?xml version="1.0" encoding="UTF-8"?>
<?xml-model href="../../schema/identified-entities.rng" type="application/xml" schematypens="http://relaxng.org/ns/structure/1.0"?>
<person xmlns="http://www.tei-c.org/ns/1.0" xml:id="NA5903">
   <persName>
      <forename>Alexander</forename>
      <surname>Moncrieff</surname>
   </persName>
   <note type="dates">
      <date>1829 - 1906</date>
   </note>
   <sex value="M"/>
   <note type="biography">
      <p>Birth: 27 George Square, Edinburgh, Scotland (17 April 1829)</p>
      <p>Death: Bandirran, Perthshire (03 August 1906)</p>
      <p>Burial: Abernethy, Perthshire</p>
      
      <p>Profession: Civil engineer</p>
      <p>Education: Edinburgh University; Aberdeen University</p>
      <p>Career: Commission in the Forfarshire Artillery (Miltia) (1825); served in the Crimea, at the siege of Sebastopol; Colonel (1878); invented the Moncrieff system of raising and lowering guns; deisgned a hydro-pneumatic carriage for guns; director of two banks; bought the estate of Bandirran, Perthshire</p>
      <p>Honours: CB 1880; KCB 1890</p>
      
      <p>Membership: Fellow</p>
      <p>Election Date: 8/06/1871</p>
   </note>
   <note type="sources">
      <p>Sources: Bulloch's Roll; DNB</p>
   </note>
</person>