<?xml version="1.0" encoding="UTF-8"?>
<?xml-model href="../../schema/identified-entities.rng" type="application/xml" schematypens="http://relaxng.org/ns/structure/1.0"?>
<person xmlns="http://www.tei-c.org/ns/1.0" xml:id="NA6125">
   <persName>
      <forename>Francis William</forename>
      <surname>Aston</surname>
   </persName>
   <note type="dates">
      <date>1877 - 1945</date>
   </note>
   <sex value="M"/>
   <note type="biography">
      <p>Birth: Harborne, Birmingham, England (01 September 1877)</p>
      <p>Death: Cambridge (20 November 1945)</p>
      
      <p>Research Field: Physics</p>
      <p>Education: Malvern College; Mason College (later Birmingham University). MA (Camb); DSc (Birm)</p>
      <p>Career: Forster Scholar studying optical rotation (1898-1900); research assistant to Sir Joseph John Thomson (FRS 1884), Cavendish Laboratory, Cambridge; Royal Aircraft Establishment, Farnborough (during World War 1); Research Fellow of Trinity College, Cambridge (1920); member of eclipse expeditions</p>
      
      <p>Membership: Fellow</p>
      <p>Election Date: 12/05/1921</p>
      <p>Medals/Prizes: Hughes Medal 1922; Royal Medal 1938; Nobel Prize (Chemistry) 1922</p>
      <p>Lectures: Bakerian 1927</p>
   </note>
   <note type="sources">
      <p>Sources: Bulloch's Roll; DNB; DSB</p>
      <p>AssocMaterial: NCUACS 101/6/01. Papers deposited Cambridge University Library (covering the period 1911-1945)</p>
      <p>Obituaries: Obituary Notices of Fellows of the Royal Society 1945-1948 vol 5 pp 635-650, plate, by G Hevesy</p>
   </note>
</person>