<?xml version="1.0" encoding="UTF-8"?>
<?xml-model href="../../schema/identified-entities.rng" type="application/xml" schematypens="http://relaxng.org/ns/structure/1.0"?>
<person xmlns="http://www.tei-c.org/ns/1.0" xml:id="NA6230">
   <persName>
      <forename>Charles</forename>
      <surname>Hutton</surname>
   </persName>
   <note type="dates">
      <date>1737 - 1823</date>
   </note>
   <sex value="M"/>
   <note type="biography">
      <p>Birth: Percy Street, Newcastle upon Tyne, Northumberland, England (14 August 1737)</p>
      <p>Death: London (27 January 1823)</p>
      <p>Burial: The family vault at Charlton, Kent</p>
      
      <p>Profession: Mathematician</p>
      <p>Research Field: Mathematics</p>
      <p>Career: Hewer in a coal pit, Long Benton; became a teacher; opened a mathematical school, Newcastle (1760), where John Scott (FRS 1793) was one of his pupils; undertook additional private coaching; Professor of Mathematics, Royal Military Academy, Woolwich (1773); resigned Professorship (1809); retired to Bedford Row, London</p>
      
      <p>Membership: Fellow</p>
      <p>Election Date: 16/06/1774</p>
      <p>Medals/Prizes: Copley Medal 1778</p>
      <p>Council: For Sec 1779-1784</p>
   </note>
   <note type="sources">
      <p>Sources: Bulloch's Roll; DNB; DSB</p>
      <p>References: Anthony Hall-Patch, 'Charles Blacker Vignoles, FRS' in NR 1993 vol 47 pp 233-242</p>
      <p>W Johnson, 'Benjamin Robins, FRS (1707-1751): New Details of His Life' in NR 1992 vol 46 pp 235-252</p>
      <p>A W Skempton, 'The Publication of Smeaton's Reports' in NR 1971 vol 26 pp 135-155</p>
      <p>Sir Gavin de Beer and R M Turton, 'John Turton, FRS, 1735-1806' in NR 1956-57 vol 12 pp 77-97</p>
      <p>J L Heilbron, 'Information technology. Encyclopaedic visions. Scientific dictionaries and the Enlightenment culture by R Yeo' in NR 2003 vol 57 pp 111-112</p>
      <p>A McConnell, 'All guns blazing. &lt;i&gt;Collected works on Benjamin Robins and Charles Hutton&lt;/i&gt;, by W Johnson' in NR 2004 vol 58 pp 102-103</p>
   </note>
</person>