<?xml version="1.0" encoding="UTF-8"?>
<?xml-model href="../../schema/identified-entities.rng" type="application/xml" schematypens="http://relaxng.org/ns/structure/1.0"?>
<person xmlns="http://www.tei-c.org/ns/1.0" xml:id="NA6409">
   <persName>
      <forename>John</forename>
      <surname>Scott</surname>
   </persName>
   <persName type="additional" subtype="title">
      <roleName>1st Earl of Eldon and Viscount Encombe</roleName>
   </persName>
   <note type="dates">
      <date>1751 - 1838</date>
   </note>
   <sex value="M"/>
   <note type="biography">
      <p>Birth: Love Lane, Newcastle upon Tyne, Northumberland, England (04 June 1751)</p>
      <p>Death: Hamilton Place, London (13 January 1838)</p>
      <p>Burial: Kingston Chapel graveyard, near Encombe, Isle of Purbeck, Dorset</p>
      
      <p>Profession: Barrister</p>
      <p>Education: Royal Grammar School, Newcastle; the school of Charles Hutton (FRS 1774); University College Oxford. BA (1770); MA (1773); DCL (1801</p>
      <p>Career: Fellow of University College, Oxford; MP for Weobley (1782-99); Solicitor General (1788-1793); Attorney General (1793-1799); Lord Chief Justice of the Common Pleas (1799); Lord Chancellor (1801-1806, 1807-1827)</p>
      <p>Honours: Kt 1788; Baron Eldon 1799; Viscount Encombe and Earl of Eldon 1821</p>
      <p>Memberships: FSA</p>
      
      <p>Membership: Fellow</p>
      <p>Election Date: 14/02/1793</p>
   </note>
   <note type="sources">
      <p>Sources: Bulloch's Roll; DNB</p>
      <p>Obituaries: Proc Roy Soc 1838 No 35 p 94</p>
      <p>References: J M Edmonds, 'The Founding of the Oxford Readership in Geology, 1818' in NR 1979-80 vol 34 pp 33-51</p>
   </note>
</person>