<?xml version="1.0" encoding="UTF-8"?>
<?xml-model href="../../schema/identified-entities.rng" type="application/xml" schematypens="http://relaxng.org/ns/structure/1.0"?>
<person xmlns="http://www.tei-c.org/ns/1.0" xml:id="NA6595">
   <persName>
      <forename>Frederick Temple Hamilton-Temple</forename>
      <surname>Blackwood</surname>
   </persName>
   <persName type="additional" subtype="title">
      <roleName>1st Marquess of Dufferin and Ava</roleName>
   </persName>
   <note type="dates">
      <date>1826 - 1902</date>
   </note>
   <sex value="M"/>
   <note type="biography">
      <p>Birth: Florence, Italy (21 June 1826)</p>
      <p>Death: Clandeboye House, Belfast (12 February 1902)</p>
      
      <p>Education: Eton; Christ Church, Oxford</p>
      <p>Career: President, Oxford Union (1847); Lord in Waiting (1854-1858); Under Secretary for India (1864-1866); Privy Councillor (1868); Governor General of Canada (1872-1878); Ambassador to St Petersburg (1879-1881); Ambassador to Constantinople (1881-1884); Viceroy of India (1884-1888); Ambassador to Rome (1889-1891); Ambassador to Paris (1891-1896); Lord Warden of the Cinque Ports (1891-1895)</p>
      <p>Honours: Baron 1850; KCB 1861; KP 1864; GCMG 1876; GCB 1883; GCSI 1884; GCIE 1887; Marquess 1888</p>
      
      <p>Membership: Fellow</p>
      <p>Election Date: 9/02/1865</p>
   </note>
   <note type="sources">
      <p>Sources: Bulloch's Roll; DNB</p>
      <p>References: Vanity Fair 09 April 1870</p>
      <p>Notes: Elected a Fellow before becoming Marquess. In R and index to BR, the name of his title is spelt Claneboye, whereas DNB gives Clandeboye.</p>
   </note>
</person>