<?xml version="1.0" encoding="UTF-8"?>
<?xml-model href="../../schema/identified-entities.rng" type="application/xml" schematypens="http://relaxng.org/ns/structure/1.0"?>
<person xmlns="http://www.tei-c.org/ns/1.0" xml:id="NA6737">
   <persName>
      <forename>Owen</forename>
      <surname>Brigstocke</surname>
   </persName>
   <note type="dates">
      <date>1679 - 1746</date>
   </note>
   <sex value="M"/>
   <note type="biography">
      <p>Baptism: 03 April 1679</p>
      <p>Death: April 1746</p>
      
      <p>Education: Eton College; Jesus College, Oxford (matriculated 1695); Middle Temple (admitted 1697)</p>
      <p>Career: Called to the Bar (1705); MP for Cardigan Boroughs (1712-1713); MP for Cardiganshire (1717-1722)</p>
      
      <p>Membership: Fellow</p>
      <p>Election Date: 30/11/1710</p>
   </note>
   <note type="sources">
      <p>Sources: Bulloch's Roll; Foster; Sedgwick; MT</p>
   </note>
</person>