<?xml version="1.0" encoding="UTF-8"?>
<?xml-model href="../../schema/identified-entities.rng" type="application/xml" schematypens="http://relaxng.org/ns/structure/1.0"?>
<person xmlns="http://www.tei-c.org/ns/1.0" xml:id="NA6809">
   <persName>
      <forename>John</forename>
      <surname>Pringle</surname>
   </persName>
   <note type="dates">
      <date>1707 - 1782</date>
   </note>
   <sex value="M"/>
   <note type="biography">
      <p>Birth: Stitchel, Roxburgh, Roxburghshire, Scotland (10 April 1707)</p>
      <p>Death: London (18 January 1782)</p>
      <p>Burial: St James's Church, Piccadilly, London</p>
      
      <p>Research Field: Medicine</p>
      <p>Honours: Bt 1766</p>
      
      <p>Membership: Fellow</p>
      <p>Election Date: 31/10/1745</p>
      <p>Medals/Prizes: Copley Medal 1752</p>
      <p>Council: PRS 1772-1778; VP 1769-1770, 1771-1772</p>
   </note>
   <note type="sources">
      <p>Sources: Bulloch's Roll; DNB; DSB; Birthplace from The Times, 10 April 2000</p>
      <p>References: A D Atkinson, 'Dr Johnson and the Royal Society' in NR 1953 vol 10 pp 131-138</p>
      <p>Egon H Kodicek and Frank G Young, 'Captain Cook and Scurvy' in NR 1969 vol 24 pp 43-63</p>
      <p>R V Jones, 'Benjamin Franklin' in NR 1976-7 vol 31 pp 201-225</p>
      <p>David Philip Miller, 'The "Hardwicke Circle": the Whig Supremacy and its Demise in the 18th-Century Royal Society' in NR 1998 vol 52 pp 73-91, plate</p>
      <p>L B Glyn, 'Israel Lyons: a short but starry career. The life of an eighteenth-century Jewish botanist and astronomer' in NR 2002 vol 56 pp 275-305</p>
      <p>M Crosland, 'Relationships between the Royal Society and the Academie des Sciences in the late eighteenth century' in NR 2005 vol 59 pp 25-34</p>
   </note>
</person>