<?xml version="1.0" encoding="UTF-8"?>
<?xml-model href="../../schema/identified-entities.rng" type="application/xml" schematypens="http://relaxng.org/ns/structure/1.0"?>
<person xmlns="http://www.tei-c.org/ns/1.0" xml:id="NA6817">
   <persName>
      <forename>Richard</forename>
      <surname>Brocklesby</surname>
   </persName>
   <note type="dates">
      <date>1722 - 1797</date>
   </note>
   <sex value="M"/>
   <note type="biography">
      <p>Birth: Minehead, Somerset, England (11 August 1722)</p>
      <p>Death: 11 December 1797</p>
      <p>Burial: The church of St Clement Danes</p>
      
      <p>Membership: Fellow</p>
      <p>Election Date: 26/02/1747</p>
   </note>
   <note type="sources">
      <p>Sources: Bulloch's Roll; DNB</p>
      <p>References: A D Atkinson, 'Dr Johnson and the Royal Society' in NR 1953 vol 10 pp 131-138</p>
   </note>
</person>