<?xml version="1.0" encoding="UTF-8"?>
<?xml-model href="../../schema/identified-entities.rng" type="application/xml" schematypens="http://relaxng.org/ns/structure/1.0"?>
<person xmlns="http://www.tei-c.org/ns/1.0" xml:id="NA7086">
   <persName>
      <forename>Thomas</forename>
      <surname>Percival</surname>
   </persName>
   <note type="dates">
      <date>1740 - 1804</date>
   </note>
   <sex value="M"/>
   <note type="biography">
      <p>Birth: Warrington, Lancashire, England (29 September 1740)</p>
      <p>Death: Manchester, Lancashire (30 August 1804)</p>
      <p>Burial: Warrington church, Lancashire</p>
      
      <p>Membership: Fellow</p>
      <p>Election Date: 7/03/1765</p>
   </note>
   <note type="sources">
      <p>Sources: Bulloch's Roll; DNB</p>
      <p>References: R W Jones, 'Dalton's unfortunate choice' in NR 2003 vol 57 pp 15-33</p>
   </note>
</person>