<?xml version="1.0" encoding="UTF-8"?>
<?xml-model href="../../schema/identified-entities.rng" type="application/xml" schematypens="http://relaxng.org/ns/structure/1.0"?>
<person xmlns="http://www.tei-c.org/ns/1.0" xml:id="NA7046">
   <persName>
      <forename>Francis</forename>
      <surname>Russell</surname>
   </persName>
   <note type="dates">
      <date> - 1795</date>
   </note>
   <sex value="M"/>
   <note type="biography">
      <p>Membership: Fellow</p>
      <p>Election Date: 15/03/1770</p>
   </note>
   <note type="sources">
      <p>Sources: Bulloch's Roll (from GM)</p>
   </note>
</person>