<?xml version="1.0" encoding="UTF-8"?>
<?xml-model href="../../schema/identified-entities.rng" type="application/xml" schematypens="http://relaxng.org/ns/structure/1.0"?>
<person xmlns="http://www.tei-c.org/ns/1.0" xml:id="NA7070">
   <persName>
      <forename>Charles Drummond</forename>
      <surname>Ellis</surname>
   </persName>
   <note type="dates">
      <date>1895 - 1980</date>
   </note>
   <sex value="M"/>
   <note type="biography">
      <p>Birth: 11 August 1895</p>
      <p>Death: 10 January 1980</p>
      
      <p>Education: Harrow School; PhD</p>
      <p>Career: Fellow of Trinity College, Cambridge; University Lecturer in Physics</p>
      <p>Honours: Kt 1946</p>
      
      <p>Membership: Fellow</p>
      <p>Election Date: 2/05/1929</p>
   </note>
   <note type="sources">
      <p>Sources: Bulloch's Roll</p>
      <p>Obituaries: Biographical Memoirs of Fellows of the Royal Society 1981 vol 27 pp 199-233, plate, by Sir Kenneth Hutchison, J A Gray and Sir Harrie Massey</p>
      <p>References: A R Mackintosh, 'The Third Man: Charles Drummond Ellis, 1895-1980' in NR 1995 vol 49 pp 277-293, plate</p>
   </note>
   <note type="keywords">
      <term>Physicist</term>
   </note>
</person>