<?xml version="1.0" encoding="UTF-8"?>
<?xml-model href="../../schema/identified-entities.rng" type="application/xml" schematypens="http://relaxng.org/ns/structure/1.0"?>
<person xmlns="http://www.tei-c.org/ns/1.0" xml:id="NA7233">
   <persName>
      <forename>Thomas</forename>
      <surname>Smith</surname>
   </persName>
   <note type="dates">
      <date>1777 - 1824</date>
   </note>
   <sex value="M"/>
   <note type="biography">
      <p>Birth: 21 January 1777</p>
      <p>Death: 15 March 1824</p>
      
      <p>Memberships: FLS</p>
      
      <p>Membership: Fellow</p>
      <p>Election Date: 25/04/1816</p>
   </note>
   <note type="sources">
      <p>Sources: Bulloch's Roll</p>
      <p>References: Christoph J Scriba, 'The Autobiography of John Wallis, FRS' in NR 1970 vol 25 pp 17-46</p>
   </note>
</person>