<?xml version="1.0" encoding="UTF-8"?>
<?xml-model href="../../schema/identified-entities.rng" type="application/xml" schematypens="http://relaxng.org/ns/structure/1.0"?>
<person xmlns="http://www.tei-c.org/ns/1.0" xml:id="NA7359">
   <persName>
      <forename>Domenico</forename>
      <surname>Ferrari</surname>
   </persName>
   <note type="dates">
      <date> - 1744</date>
   </note>
   <sex value="M"/>
   <note type="biography">
      <p>Birth: Naples, Italy</p>
      <p>Death: The Earl of Leicester's house, Great Russell Street, Bloomsbury Square (1744)</p>
      
      <p>Profession: Barrister</p>
      <p>Librarian</p>
      <p>Education: LLD</p>
      <p>Career: Practised as an advocate in Naples; met a member of Sir Thomas Coke's (later the Earl of Leicester's) household by whom he was converted to Anglicanism; Librarian to the Earl of Leicester; died of the stone; left a valuable library to the Earl of Leicester</p>
      
      <p>Membership: Fellow</p>
      <p>Election Date: 14/11/1723</p>
   </note>
   <note type="sources">
      <p>Sources: Bulloch's Roll</p>
      <p>References: 'Gentleman's Magazine' 1744, p282</p>
      <p>Notes: Proposed by James Jurin, on behalf of Richard Meade</p>
   </note>
</person>