<?xml version="1.0" encoding="UTF-8"?>
<?xml-model href="../../schema/identified-entities.rng" type="application/xml" schematypens="http://relaxng.org/ns/structure/1.0"?>
<person xmlns="http://www.tei-c.org/ns/1.0" xml:id="NA7423">
   <persName>
      <forename>Charles</forename>
      <surname>Burney</surname>
   </persName>
   <note type="dates">
      <date>1757 - 1817</date>
   </note>
   <sex value="M"/>
   <note type="biography">
      <p>Birth: King's Lynn, Norfolk, England (04 December 1757)</p>
      <p>Death: Deptford, Kent (28 December 1817)</p>
      
      <p>Education: Charterhouse School; Caius College, Cambridge; MA (1781) King's College Aberdeen; LLD (Aberdeen); LLD (1792, Glasgow); MA (1808, Cambridge); DD (1812, from Archbishop of Canterbury?)</p>
      <p>Career: School master, Highgate and Chiswick; opened his own school, Hammersmith (1786); moved to a school at Greenwich (1793); took Holy Orders; appointed to the Rectory of Cliffe, Kent, and of St Paul's Deptford; Chaplain to the King; Prebend of Lincoln; wrote on the Greek Classics; his collection of books was purchased for the nation for £13,500, in the British Museum as the Burney Collection (13,000 printed works); died of apoplexy</p>
      
      <p>Membership: Fellow</p>
      <p>Election Date: 25/02/1802</p>
   </note>
   <note type="sources">
      <p>Sources: Bulloch's Roll; DNB</p>
   </note>
</person>