<?xml version="1.0" encoding="UTF-8"?>
<?xml-model href="../../schema/identified-entities.rng" type="application/xml" schematypens="http://relaxng.org/ns/structure/1.0"?>
<person xmlns="http://www.tei-c.org/ns/1.0" xml:id="NA8058">
   <persName>
      <forename>Julius von</forename>
      <surname>Haast</surname>
   </persName>
   <note type="dates">
      <date>? 1824 - 1887</date>
   </note>
   <sex value="M"/>
   <note type="biography">
      <p>Birth: Bonn, Germany (01 May 1822 or 01 May 1824)</p>
      <p>Death: Wellington, New Zealand (15 or 16 August 1887)</p>
      
      <p>Research Field: Geology, mineralogy</p>
      <p>Education: BonnPhD</p>
      <p>Career: Travelled in Europe; sailed to New Zealand (1858); appointed to explore the south west part of Nelson (1859); Surveyor General, Province of Canterbury, New Zealand (1861); Provincial Geologist; founded the Canterbury Museum (1866); died of heart disease</p>
      <p>Honours: CMG 1883; KCMG 1886</p>
      <p>Memberships: FGS; FLS</p>
      
      <p>Membership: Fellow</p>
      <p>Election Date: 6/06/1867</p>
   </note>
   <note type="sources">
      <p>Sources: Bulloch's Roll; DSB</p>
      <p>Authority: First Altname from BR, second from DSB</p>
      <p>Obituaries: Proc Roy Soc 1889 vol 46 pp xxiv-xxvi signed by W L B</p>
      <p>References: Robin J H Clark and Michael J Kelly, 'New Zealand, New Zealanders and the Royal Society' in NR 1994 vol 48 pp 263-281</p>
      <p>R W Home, 'The Royal Society and the Empire: the colonial and Commonwealth Fellowship. Part 2. After 1847' in NR 2003 vol 57 pp 47-84</p>
      <p>Notes: DSB gives dates of birth and death as 01 May 1822 and 16 August 1887</p>
   </note>
</person>