<?xml version="1.0" encoding="UTF-8"?>
<?xml-model href="../../schema/identified-entities.rng" type="application/xml" schematypens="http://relaxng.org/ns/structure/1.0"?>
<person xmlns="http://www.tei-c.org/ns/1.0" xml:id="NA8204">
   <persName>
      <forename>Cecil Clifford</forename>
      <surname>Dobell</surname>
   </persName>
   <note type="dates">
      <date>1886 - 1949</date>
   </note>
   <sex value="M"/>
   <note type="biography">
      <p>Birth: Birkenhead, Cheshire, England (22 February 1886)</p>
      <p>Death: London (23 December 1949)</p>
      
      <p>Research Field: Protozoology</p>
      <p>Education: MA (Camb)</p>
      
      <p>Membership: Fellow</p>
      <p>Election Date: 2/05/1918</p>
   </note>
   <note type="sources">
      <p>Sources: Bulloch's Roll; DSB</p>
      <p>Obituaries: Obituary Notices of Fellows of the Royal Society 1950-1951 vol 7 pp 35-61, plate, by Cecil A Hoare and Doris L Mackinnon</p>
      <p>References: A R Hall, 'The Leeuwenhoek Lecture, 1988. Antoni van Leeuwenhoek 1632-1723' in NR 1989 vol 43 pp 249-273</p>
      <p>Brian J Ford, 'The Leeuwenhoekiana of Clifford Dobell (1886-1949)' in NR 1986-87 vol 41 pp 95-105, plate</p>
      <p>H Gest, 'The Discovery of Microorganisms by Robert Hooke and Antoni von Leeuwenhoek, Fellows of the Royal Society' in NR 2004 vol 58 pp 187-201</p>
   </note>
</person>