<?xml version="1.0" encoding="UTF-8"?>
<?xml-model href="../../schema/identified-entities.rng" type="application/xml" schematypens="http://relaxng.org/ns/structure/1.0"?>
<person xmlns="http://www.tei-c.org/ns/1.0" xml:id="HENSLOW-IDENT-9" status="released">
    <persName>
        <forename>Richard</forename>
        <surname>Twopeny</surname>
    </persName>
    <persName xml:id="canonical">Twopeny, Richard</persName>
    <note type="dates"><date>06.10.1794 - 03.10.1871</date></note>
    <sex value="M"/>
    <note type="biography">
        <p>Born 6 October 1794 at Little Casterton, Rutland. Educated at Rugby School and St. Johns College, Cambridge. Matriculated Michaelmas term 1812 and graduated in 1816 BA, 8th Wrangler. Fellow of St. Johns 1817-30, Chaplain of Horningsea 1826-29. Moved to Oxfordshire in 1829 to become Vicar of North Stoke with Ipsden, and died there in 1871.</p></note>
</person>