<?xml version="1.0" encoding="UTF-8"?>
<?xml-model href="../../schema/identified-entities.rng" type="application/xml" schematypens="http://relaxng.org/ns/structure/1.0"?>
<person xmlns="http://www.tei-c.org/ns/1.0" xml:id="PERSON194">
    
<persName>
<forename>Mary Lucy</forename>
<surname>Cole, née Fox Strangways</surname>
</persName>
    <idno>Cole-M</idno>
    <note type="biography">Lady Mary Lucy Cole, née Fox Strangways  (11 Feb 1776 -  3 Feb 1855);  m. Thomas Mansel Talbot (1747-1813), Feb 1794; m. Capt Sir Christopher Cole (1770-1836), 28 Apr 1815; WHFT's aunt</note>
</person>